{"expireTime":9007200901738460000,"key":"transformer-remark-markdown-html-ast-b3c0667fd86617de5fd7ff8e13be8205-gatsby-remark-images-","val":{"type":"root","children":[{"type":"element","tagName":"p","properties":{},"children":[{"type":"text","value":"Supply of machines for the medium multi-products production of assembly of printed circuit boards of various complexity. Latest technology and stability. Operational reliability and quick changeover. A series of flexible machines with maximum capabilities.","position":{"start":{"line":2,"column":1,"offset":1},"end":{"line":2,"column":257,"offset":257}}}],"position":{"start":{"line":2,"column":1,"offset":1},"end":{"line":2,"column":257,"offset":257}}}],"position":{"start":{"line":1,"column":1,"offset":0},"end":{"line":7,"column":1,"offset":262}}}}