{
    "id": "6-smt-juki-loader-mb760-ru",
    "ru": "оборудование-для-монтажа/поверхностный-монтаж/перемещение-печатных-плат/загрузчик-разгрузчик-плат",
    "ua": "ua/обладнання-для-монтажу/поверхневий-монтаж/переміщення-друкованих-плат/завантажувач-розвантажувач-плат",
    "title": "mb760",
    "bigtitle": "MB760 Устройство для загрузки печатных плат со стопки - Destacker",
    "category": "Загрузчик - Разгрузчик плат",
    "excerpt": "Оборудование загрузки печатных плат со стопки на производственную линию. Оборудование для загрузки плат без накопителя плат. Монтаж печатных плат SMT",
    "keywords": "перемещение печатных плат, конвейеры для печатных плат, загрузчик печатных плат, разгрузчик печатных плат, конвейерные системы,транспортировка печатных плат, loader, unloader, Destacker",
    "short_desc": "Автоматический загрузчик печатных плат из стопки на конвейер линии SMT. Работает без  магазинов (накопителей плат) с пустыми платами. Может устанавливается в любой части линии. После окончания плат устройство может работать как обычный конвейер 500мм.",
    "techover_title": "",
    "techover": "Оборудование для загрузки печатных плат со стопки на производственную линию - Destacker.  Загрузчик работает без  магазинов для плат.",
    "techfeat_title": "",
    "techfeat": [
        {
            "id": "tech-1",
            "feat": "Ручка для легкой регулировки под толщину плат"
        },
        {
            "id": "tech-2",
            "feat": "Световая индикация статуса работы"
        },
        {
            "id": "tech-3",
            "feat": "Моторизованная регулировка ширины"
        },
        {
            "id": "tech-4",
            "feat": "PLC контроллер"
        },
        {
            "id": "tech-5",
            "feat": "SMEMA интерфейс"
        }
    ],
    "techspec": [
        {
            "id": "tech-1",
            "spec": "Размер печатных плат до 508х470мм"
        },
        {
            "id": "tech-2",
            "spec": "Толщина плат  0.7 – 3 мм"
        },
        {
            "id": "tech-3",
            "spec": "Высота стопки до 200 мм"
        },
        {
            "id": "tech-4",
            "spec": "Вес стопки до 20 кг"
        },
        {
            "id": "tech-5",
            "spec": "SMEMA интерфейс"
        },
        {
            "id": "tech-5",
            "spec": "габаритные размеры - 500х800х1150мм"
        }
    ],
    "techoption": [
        {
            "id": "tech-1",
            "option": "Автоматическая регулировка ширины"
        },
        {
            "id": "tech-2",
            "option": "Блок автоматического регулирования ширины"
        }
    ],
    "tagline": "Загрузчики для плат",
    "image": "../../../images/bg/machines/conveyers/mb760.jpg",
    "seoimage": "../../../images/bg/machines/storage/xsc-300-01.jpg",
    "brochure": "https://drive.google.com/file/d/11dSWEv4FcQeDoDieoJy1nx7tsxOuoH8m/view?usp=sharing",
    "is_featured": true,
    "banner_image": "../../../images/bg/machines/smt/conveyer/loader-baner.jpg",

    "results": "Очень коротко о самом главном :) Быстрые ответы на очень часто задаваемые вопросы.",
    "faq": [
        {
            "id": "highly-service-faq-1",
            "title": "Для чего это?",
            "desc": "Применяется в начале линии для автоматической загрузки печатных плат на конвейер. Рекомендуется для линии поверхностного монтажа (SMT)  в условиях серийного производства."
        },
        {
            "id": "highly-service-faq-2",
            "title": "Где используют?",
            "desc": "применяется для автоматизации загрузки печатных плат в производственную линию. Рекомендуется для серийного производства монтажа плат."
        },
        {
            "id": "highly-service-faq-3",
            "title": "Сколько стоит?",
            "desc": "может комплектоваться дополнительным оборудованием и программным обеспечением  под изделия заказчика, что влияет на цену оборудования. Обращайтесь к нашим специалистам. Прайс-листа нет."
        },
        {
            "id": "highly-service-faq-4",
            "title": "Как заказать?",
            "desc": "может иметь разную конфигурацию и дополнительное оборудование. Составьте техническое задание для определения состава оборудования и отправьте нашим специалистам."
        }
    ],
    "video": {
        "preview_image": "../../../images/bg/machines/conveyers/mb760.jpg",
        "video_link": ""
    }
}